pytcp_serial_handler/__init__.py
pytcp_serial_handler/handler.py
pytcp_serial_handler/pems_consts.py
pytcp_serial_handler/pems_types.py
pytcp_serial_handler/utlis.py
pyfrigel_tcp_serial_handler-1.10.dist-info/LICENSE.txt
pyfrigel_tcp_serial_handler-1.10.dist-info/METADATA
pyfrigel_tcp_serial_handler-1.10.dist-info/WHEEL
pyfrigel_tcp_serial_handler-1.10.dist-info/top_level.txt
pyfrigel_tcp_serial_handler-1.10.dist-info/RECORD
