Metadata-Version: 2.1
Name: pyfrigel_tcp_serial_handler
Version: 1.10
Summary: Frigel TCP to serial handler for PEMS protocol
Home-page: http://pypi.python.org/pypi/pyfrigel-tcp-serial-handler/
License: LICENSE.txt
License-File: LICENSE.txt
Requires-Dist: pyserial
Requires-Dist: pyserial-asyncio
